src/SymmetryGroups.py
src/__init__.py
src/__main__.py
src/align_projection_2d.py
src/align_volumes_3d.py
src/common_finufft.py
src/commonline_R2.py
src/cryo_fetch_emdID.py
src/cryo_project_itay_finufft.py
src/dev_utils.py
src/emalign_input.py
src/fastrotate3d.py
src/fsc.py
src/genRotationsGrid.py
src/gentestdata.py
src/main.py
src/rand_rots.py
src/read_write.py
src/register_translations_3d.py
src/reshift_vol.py
EMalign-1.0.4.dist-info/LICENSE
EMalign-1.0.4.dist-info/METADATA
EMalign-1.0.4.dist-info/WHEEL
EMalign-1.0.4.dist-info/entry_points.txt
EMalign-1.0.4.dist-info/top_level.txt
EMalign-1.0.4.dist-info/RECORD
