Metadata-Version: 2.1
Name: EMalign
Version: 1.0.4
Summary: EM align
Home-page: https://github.com/ShkolniskyLab/EMalign
Author: Yoel Shkolnisky
Author-email: yoelsh@tauex.tau.ac.il
License: GNU General Public License v3.0
Requires-Python: ~=3.6
License-File: LICENSE
Requires-Dist: numpy (>=1.16)
Requires-Dist: mrcfile
Requires-Dist: scipy (>=1.3)
Requires-Dist: pyfftw
Requires-Dist: finufft
